choice_learn/__init__.py
choice_learn/basket_models/__init__.py
choice_learn/basket_models/alea_carta.py
choice_learn/basket_models/base_basket_model.py
choice_learn/basket_models/basic_attention_model.py
choice_learn/basket_models/data/__init__.py
choice_learn/basket_models/data/basket_dataset.py
choice_learn/basket_models/data/preprocessing.py
choice_learn/basket_models/datasets/__init__.py
choice_learn/basket_models/datasets/bakery.py
choice_learn/basket_models/datasets/synthetic_dataset.py
choice_learn/basket_models/self_attention_model.py
choice_learn/basket_models/shopper.py
choice_learn/basket_models/utils/__init__.py
choice_learn/basket_models/utils/permutation.py
choice_learn/data/__init__.py
choice_learn/data/choice_dataset.py
choice_learn/data/indexer.py
choice_learn/data/storage.py
choice_learn/data/store.py
choice_learn/datasets/__init__.py
choice_learn/datasets/base.py
choice_learn/datasets/cache/.gitkeep
choice_learn/datasets/data/HC.csv.gz
choice_learn/datasets/data/ModeCanada.csv.gz
choice_learn/datasets/data/__init__.py
choice_learn/datasets/data/car.csv.gz
choice_learn/datasets/data/electricity.csv.gz
choice_learn/datasets/data/heating_data.csv.gz
choice_learn/datasets/data/swissmetro.csv.gz
choice_learn/datasets/data/ta_feng.csv.zip
choice_learn/datasets/data/train_data.csv.gz
choice_learn/datasets/expedia.py
choice_learn/datasets/tafeng.py
choice_learn/models/__init__.py
choice_learn/models/base_model.py
choice_learn/models/baseline_models.py
choice_learn/models/conditional_logit.py
choice_learn/models/halo_mnl.py
choice_learn/models/latent_class_base_model.py
choice_learn/models/latent_class_mnl.py
choice_learn/models/learning_mnl.py
choice_learn/models/nested_logit.py
choice_learn/models/reslogit.py
choice_learn/models/rumnet.py
choice_learn/models/simple_mnl.py
choice_learn/models/tastenet.py
choice_learn/tf_ops.py
choice_learn/toolbox/__init__.py
choice_learn/toolbox/assortment_optimizer.py
choice_learn/toolbox/gurobi_opt.py
choice_learn-1.3.1.dist-info/METADATA
choice_learn-1.3.1.dist-info/WHEEL
choice_learn-1.3.1.dist-info/licenses/LICENSE.md
choice_learn-1.3.1.dist-info/RECORD
