Metadata-Version: 2.4
Name: choice-learn
Version: 1.3.1
Summary: Large-scale choice modeling through the lens of machine learning.
License-Expression: MIT
License-File: LICENSE.md
Keywords: discrete,choice,model,machine,learning,assortment,pricing,retail,supermarket
Author: Vincent Auriau
Author-email: vincent.auriau.dev@gmail.com
Maintainer: Vincent Auriau
Maintainer-email: vincent.auriau.dev@gmail.com
Requires-Python: >=3.9,<3.13
Classifier: License :: OSI Approved :: MIT License
Classifier: Programming Language :: Python :: 3
Classifier: Programming Language :: Python :: 3.9
Classifier: Programming Language :: Python :: 3.10
Classifier: Programming Language :: Python :: 3.11
Classifier: Programming Language :: Python :: 3.12
Classifier: Topic :: Scientific/Engineering
Classifier: Topic :: Scientific/Engineering :: Mathematics
Classifier: Topic :: Software Development
Provides-Extra: gurobi
Provides-Extra: ortools
Requires-Dist: gurobipy (>=11.0) ; extra == "gurobi"
Requires-Dist: numpy (>=1.24)
Requires-Dist: ortools (>=9.6) ; extra == "ortools"
Requires-Dist: pandas (>=1.5.3)
Requires-Dist: tensorflow (>=2.14,<2.17.0)
Requires-Dist: tensorflow-probability (>=0.22)
Requires-Dist: tf_keras (<3)
Requires-Dist: tqdm (>=4.0.0)
Project-URL: Bug Tracker, https://github.com/artefactory/choice-learn/issues
Project-URL: Documentation, https://artefactory.github.io/choice-learn
Project-URL: Homepage, https://github.com/artefactory/choice-learn
Project-URL: Repository, https://github.com/artefactory/choice-learn
